LICENSE
MANIFEST.in
README.md
setup.cfg
setup.py
pyiArduinoI2Cexpander/__init__.py
pyiArduinoI2Cexpander/iarduino_I2C_Expander.cpp
pyiArduinoI2Cexpander/iarduino_I2C_Expander.h
pyiArduinoI2Cexpander/iarduino_I2C_Expander.pxd
pyiArduinoI2Cexpander/iarduino_I2C_PI.cpp
pyiArduinoI2Cexpander/iarduino_I2C_PI.h
pyiArduinoI2Cexpander/pyiArduinoI2Cexpander.cpp
pyiArduinoI2Cexpander/pyiArduinoI2Cexpander.pyx
pyiArduinoI2Cexpander/setup.py
pyiArduinoI2Cexpander.egg-info/PKG-INFO
pyiArduinoI2Cexpander.egg-info/SOURCES.txt
pyiArduinoI2Cexpander.egg-info/dependency_links.txt
pyiArduinoI2Cexpander.egg-info/top_level.txt
pyiArduinoI2Cexpander/cpp/FindDevices.cpp
pyiArduinoI2Cexpander/cpp/NewAddress.cpp
pyiArduinoI2Cexpander/cpp/analogAveraging.cpp
pyiArduinoI2Cexpander/cpp/analogRead.cpp
pyiArduinoI2Cexpander/cpp/analogWrite.cpp
pyiArduinoI2Cexpander/cpp/digitalRead.cpp
pyiArduinoI2Cexpander/cpp/digitalWrite.cpp
pyiArduinoI2Cexpander/cpp/freqPWM.cpp
pyiArduinoI2Cexpander/cpp/getVersion.cpp
pyiArduinoI2Cexpander/cpp/levelRead.cpp
pyiArduinoI2Cexpander/cpp/pinMode.cpp
pyiArduinoI2Cexpander/cpp/pinOutScheme.cpp
pyiArduinoI2Cexpander/cpp/pinPull.cpp
pyiArduinoI2Cexpander/cpp/reset.cpp
pyiArduinoI2Cexpander/cpp/servoAttach.cpp
pyiArduinoI2Cexpander/cpp/servoWrite.cpp
pyiArduinoI2Cexpander/cpp/servoWriteMicroseconds.cpp
pyiArduinoI2Cexpander/examples/FindDevices.py
pyiArduinoI2Cexpander/examples/NewAddress.py
pyiArduinoI2Cexpander/examples/analogAveraging.py
pyiArduinoI2Cexpander/examples/analogRead.py
pyiArduinoI2Cexpander/examples/analogWrite.py
pyiArduinoI2Cexpander/examples/digitalRead.py
pyiArduinoI2Cexpander/examples/digitalWrite.py
pyiArduinoI2Cexpander/examples/freqPWM.py
pyiArduinoI2Cexpander/examples/getVersion.py
pyiArduinoI2Cexpander/examples/levelRead.py
pyiArduinoI2Cexpander/examples/pinMode.py
pyiArduinoI2Cexpander/examples/pinOutScheme.py
pyiArduinoI2Cexpander/examples/pinPull.py
pyiArduinoI2Cexpander/examples/reset.py
pyiArduinoI2Cexpander/examples/servoAttach.py
pyiArduinoI2Cexpander/examples/servoWrite.py
pyiArduinoI2Cexpander/examples/servoWriteMicroseconds.py